<?xml version="1.0" encoding="utf-8"?>
<annotation>
<folder>bee</folder>
<filename>38821153284_b6afd82781_w.jpg</filename>
<path>/content/drive/MyDrive/tf_workspace/Images/Classification_Images/trainFD/38821153284_b6afd82781_w.jpg</path>
<source>
<database>Unknown</database>
</source>
<size>
<width>400</width>
<height>267</height>
<depth>3</depth>
</size>
<segmented>0</segmented>
<object>
<name>insect</name>
<pose>Unspecified</pose>
<truncated>1</truncated>
<difficult>0</difficult>
<bndbox>
<xmin>1</xmin>
<ymin>51</ymin>
<xmax>296</xmax>
<ymax>247</ymax>
</bndbox>
</object>
</annotation>