<?xml version="1.0" encoding="utf-8"?>
<annotation>
<folder>bee</folder>
<filename>4592106078_92ca59dae4_n.jpg</filename>
<path>/content/drive/MyDrive/tf_workspace/Images/Classification_Images/trainFD/4592106078_92ca59dae4_n.jpg</path>
<source>
<database>Unknown</database>
</source>
<size>
<width>320</width>
<height>252</height>
<depth>3</depth>
</size>
<segmented>0</segmented>
<object>
<name>bee</name>
<pose>Unspecified</pose>
<truncated>0</truncated>
<difficult>0</difficult>
<bndbox>
<xmin>41</xmin>
<ymin>72</ymin>
<xmax>226</xmax>
<ymax>183</ymax>
</bndbox>
</object>
</annotation>