<?xml version="1.0" encoding="utf-8"?>
<annotation>
<folder>bee_select</folder>
<filename>5255778391_4021831df9_m.jpg</filename>
<path>/content/drive/MyDrive/tf_workspace/Images/Classification_Images/trainFD/5255778391_4021831df9_m.jpg</path>
<source>
<database>Unknown</database>
</source>
<size>
<width>200</width>
<height>240</height>
<depth>3</depth>
</size>
<segmented>0</segmented>
<object>
<name>bee</name>
<pose>Unspecified</pose>
<truncated>0</truncated>
<difficult>0</difficult>
<bndbox>
<xmin>77</xmin>
<ymin>52</ymin>
<xmax>162</xmax>
<ymax>170</ymax>
</bndbox>
</object>
</annotation>