<?xml version="1.0" encoding="utf-8"?>
<annotation>
<folder>bee</folder>
<filename>5603959233_8415e269f7_m.jpg</filename>
<path>/content/drive/MyDrive/tf_workspace/Images/Classification_Images/trainFD/5603959233_8415e269f7_m.jpg</path>
<source>
<database>Unknown</database>
</source>
<size>
<width>240</width>
<height>231</height>
<depth>3</depth>
</size>
<segmented>0</segmented>
<object>
<name>insect</name>
<pose>Unspecified</pose>
<truncated>0</truncated>
<difficult>0</difficult>
<bndbox>
<xmin>71</xmin>
<ymin>36</ymin>
<xmax>171</xmax>
<ymax>169</ymax>
</bndbox>
</object>
</annotation>