<?xml version="1.0" encoding="utf-8"?>
<annotation>
<folder>bee</folder>
<filename>B00035.jpg</filename>
<path>/content/drive/MyDrive/tf_workspace/Images/Classification_Images/testFD/B00035.jpg</path>
<source>
<database>Unknown</database>
</source>
<size>
<width>640</width>
<height>640</height>
<depth>3</depth>
</size>
<segmented>0</segmented>
<object>
<name>vespula</name>
<pose>Unspecified</pose>
<truncated>0</truncated>
<difficult>0</difficult>
<bndbox>
<xmin>287</xmin>
<ymin>172</ymin>
<xmax>415</xmax>
<ymax>439</ymax>
</bndbox>
</object>
</annotation>